tiscontrol/__init__.py
tiscontrol/tiscontrol.py
tiscontrol-0.0.11.dist-info/LICENSE
tiscontrol-0.0.11.dist-info/METADATA
tiscontrol-0.0.11.dist-info/WHEEL
tiscontrol-0.0.11.dist-info/top_level.txt
tiscontrol-0.0.11.dist-info/RECORD
