Metadata-Version: 2.1
Name: tiscontrol
Version: 0.0.11
Summary: Python library to provide a reliable communication link with TIS  Products
Home-page: https://github.com/GeoffAtHome/lightwave
Author: tiscontrol
Author-email: gopaltis93@gmail.com
License: MIT
Keywords: tiscontrol
License-File: LICENSE
